.gitignore
.gitmodules
CMakeLists.txt
LICENSE.md
README.md
poetry.lock
pyproject.toml
setup.py
.github/workflows/build_and_publish.yml
examples/.gitignore
examples/high_level_example.py
examples/low_level_example.py
examples/samples/english.wav
examples/samples/spanish.wav
tests/__init__.py
vendor/whisper.cpp/.gitignore
vendor/whisper.cpp/.gitmodules
vendor/whisper.cpp/CMakeLists.txt
vendor/whisper.cpp/LICENSE
vendor/whisper.cpp/Makefile
vendor/whisper.cpp/README.md
vendor/whisper.cpp/ggml-cuda.cu
vendor/whisper.cpp/ggml-cuda.h
vendor/whisper.cpp/ggml-metal.h
vendor/whisper.cpp/ggml-metal.m
vendor/whisper.cpp/ggml-metal.metal
vendor/whisper.cpp/ggml-opencl.cpp
vendor/whisper.cpp/ggml-opencl.h
vendor/whisper.cpp/ggml.c
vendor/whisper.cpp/ggml.h
vendor/whisper.cpp/whisper.cpp
vendor/whisper.cpp/whisper.h
vendor/whisper.cpp/.github/workflows/bindings-go.yml
vendor/whisper.cpp/.github/workflows/bindings-ruby.yml
vendor/whisper.cpp/.github/workflows/build.yml
vendor/whisper.cpp/.github/workflows/examples.yml
vendor/whisper.cpp/bindings/CMakeLists.txt
vendor/whisper.cpp/bindings/go/.gitignore
vendor/whisper.cpp/bindings/go/LICENSE
vendor/whisper.cpp/bindings/go/Makefile
vendor/whisper.cpp/bindings/go/README.md
vendor/whisper.cpp/bindings/go/doc.go
vendor/whisper.cpp/bindings/go/go.mod
vendor/whisper.cpp/bindings/go/go.sum
vendor/whisper.cpp/bindings/go/params.go
vendor/whisper.cpp/bindings/go/whisper.go
vendor/whisper.cpp/bindings/go/whisper_test.go
vendor/whisper.cpp/bindings/go/examples/go-model-download/context.go
vendor/whisper.cpp/bindings/go/examples/go-model-download/main.go
vendor/whisper.cpp/bindings/go/examples/go-whisper/color.go
vendor/whisper.cpp/bindings/go/examples/go-whisper/flags.go
vendor/whisper.cpp/bindings/go/examples/go-whisper/main.go
vendor/whisper.cpp/bindings/go/examples/go-whisper/process.go
vendor/whisper.cpp/bindings/go/pkg/whisper/consts.go
vendor/whisper.cpp/bindings/go/pkg/whisper/context.go
whisper_cpp_pybind.egg-info/PKG-INFO
whisper_cpp_pybind.egg-info/SOURCES.txt
whisper_cpp_pybind.egg-info/dependency_links.txt
whisper_cpp_pybind.egg-info/requires.txt
whisper_cpp_pybind.egg-info/top_level.txt