Metadata-Version: 2.1
Name: whisper-cpp-pybind
Version: 0.1.3
Summary: A Python wrapper for whisper.cpp
Author: sphantix
Author-email: sphantix@gmail.com
License: MIT
Classifier: Programming Language :: Python :: 3
Classifier: Programming Language :: Python :: 3.7
Classifier: Programming Language :: Python :: 3.8
Classifier: Programming Language :: Python :: 3.9
Classifier: Programming Language :: Python :: 3.10
Classifier: Programming Language :: Python :: 3.11
Requires-Python: >=3.7
License-File: LICENSE.md
Requires-Dist: numpy>=1.20.0
